{
  "project_info": {
    "project_number": "1063272943073",
    "project_id": "ouluva-50a13",
    "storage_bucket": "ouluva-50a13.firebasestorage.app"
  },
  "client": [
    {
      "client_info": {
        "mobilesdk_app_id": "1:1063272943073:android:582c98197be28c843716a0",
        "android_client_info": {
          "package_name": "com.example.psoas_va_mobile"
        }
      },
      "oauth_client": [
        {
          "client_id": "1063272943073-hrkvfjp5507mdstqn1evuabjbbrodvhg.apps.googleusercontent.com",
          "client_type": 3
        }
      ],
      "api_key": [
        {
          "current_key": "AIzaSyAcjZ5bSVg-NrujehfTWxG0M3JKaEqDmyQ"
        }
      ],
      "services": {
        "appinvite_service": {
          "other_platform_oauth_client": [
            {
              "client_id": "1063272943073-hrkvfjp5507mdstqn1evuabjbbrodvhg.apps.googleusercontent.com",
              "client_type": 3
            }
          ]
        }
      }
    }
  ],
  "configuration_version": "1"
}